cameo_eco_query/__init__.py
cameo_eco_query/config.py
cameo_eco_query/gmap_utils.py
cameo_eco_query/openai_utils.py
cameo_eco_query/query_handler.py
cameo_eco_query-0.2.0.dist-info/METADATA
cameo_eco_query-0.2.0.dist-info/WHEEL
cameo_eco_query-0.2.0.dist-info/top_level.txt
cameo_eco_query-0.2.0.dist-info/RECORD
