Metadata-Version: 2.1
Name: cameo-eco-query
Version: 0.2.0
Summary: cameo_eco_query1
Home-page: https://github.com/bohachu/cameo-eco-query
Author: JcXGTcW
Author-email: jcxgtcw@cameo.tw
License: UNKNOWN
Platform: UNKNOWN
Classifier: Programming Language :: Python :: 3
Classifier: License :: OSI Approved :: MIT License
Classifier: Operating System :: OS Independent
Requires-Python: >=3.6
Requires-Dist: openai ==0.27.4
Requires-Dist: python-dotenv ==0.15.0
